CHANGES.txt
README.txt
bootstrap.py
buildout.cfg
setup.py
src/keas/__init__.py
src/keas.googlemap.egg-info/PKG-INFO
src/keas.googlemap.egg-info/SOURCES.txt
src/keas.googlemap.egg-info/dependency_links.txt
src/keas.googlemap.egg-info/namespace_packages.txt
src/keas.googlemap.egg-info/not-zip-safe
src/keas.googlemap.egg-info/requires.txt
src/keas.googlemap.egg-info/top_level.txt
src/keas/googlemap/README.txt
src/keas/googlemap/__init__.py
src/keas/googlemap/apikey.py
src/keas/googlemap/apikey.zcml
src/keas/googlemap/configure.zcml
src/keas/googlemap/geocode.py
src/keas/googlemap/interfaces.py
src/keas/googlemap/jsoncompat.py
src/keas/googlemap/testing.py
src/keas/googlemap/tests.py
src/keas/googlemap/browser/README.txt
src/keas/googlemap/browser/__init__.py
src/keas/googlemap/browser/configure.zcml
src/keas/googlemap/browser/google-map.pt
src/keas/googlemap/browser/interfaces.py
src/keas/googlemap/browser/keas.googlemap.js
src/keas/googlemap/browser/markermanager.js
src/keas/googlemap/browser/tests.py
src/keas/googlemap/demo/__init__.py
src/keas/googlemap/demo/app.zcml
src/keas/googlemap/demo/browser.py
src/keas/googlemap/demo/configure.zcml
src/keas/googlemap/demo/demo.pt
src/keas/googlemap/demo/interfaces.py
src/keas/googlemap/demo/jquery-1.2.3.js
src/keas/googlemap/demo/markers.pt
src/keas/googlemap/demo/template.pt