Metadata-Version: 1.0
Name: keas.googlemap
Version: 0.5.1
Summary: Integration of Google Maps with Zope 3
Home-page: http://pypi.python.org/pypi/keas.googlemap
Author: Paul Carduner, Keas, Inc., and the Zope Community
Author-email: zope3-dev@zope.org
License: ZPL 2.1
Keywords: zope google maps
Platform: UNKNOWN
Classifier: Development Status :: 4 - Beta
Classifier: Environment :: Web Environment
Classifier: Intended Audience :: Developers
Classifier: License :: OSI Approved :: Zope Public License
Classifier: Programming Language :: Python
Classifier: Natural Language :: English
Classifier: Operating System :: OS Independent
Classifier: Topic :: Internet :: WWW/HTTP
Classifier: Framework :: Zope3
